funasr_client/__init__.py
funasr_client/__main__.py
funasr_client/async_client.py
funasr_client/base_client.py
funasr_client/cli.py
funasr_client/client.py
funasr_client/factory.py
funasr_client/file_asr.py
funasr_client/mic_asr.py
funasr_client/py.typed
funasr_client/types.py
funasr_client/utils.py
funasr_client-0.1.6.dist-info/METADATA
funasr_client-0.1.6.dist-info/WHEEL
funasr_client-0.1.6.dist-info/entry_points.txt
funasr_client-0.1.6.dist-info/licenses/LICENSE
funasr_client-0.1.6.dist-info/RECORD
