Metadata-Version: 2.4
Name: funasr-client
Version: 0.1.6
Summary: Easy-to-use client for FunASR runtime server.
Project-URL: homepage, https://github.com/atomiechen/FunASR-Client
Project-URL: issues, https://github.com/atomiechen/FunASR-Client/issues
Project-URL: changelog, https://github.com/atomiechen/FunASR-Client/blob/main/CHANGELOG.md
Author-email: Atomie CHEN <atomic_cwh@163.com>
License-File: LICENSE
Keywords: asr,asynchronous,asyncio,funasr,funasr-client,websocket,websockets
Classifier: License :: OSI Approved :: MIT License
Classifier: Operating System :: OS Independent
Classifier: Programming Language :: Python :: 3
Requires-Python: >=3.8
Requires-Dist: typing-extensions>=4.13.2
Requires-Dist: websockets>=13.1
Provides-Extra: mic
Requires-Dist: pyaudio>=0.2.14; extra == 'mic'
